hack4u/__init__.py
hack4u/courses.py
hack4u/utils.py
KattoDev-0.1.0.dist-info/METADATA
KattoDev-0.1.0.dist-info/WHEEL
KattoDev-0.1.0.dist-info/top_level.txt
KattoDev-0.1.0.dist-info/RECORD
