Metadata-Version: 2.1
Name: KattoDev
Version: 0.1.0
Summary: Una prueba para mi primer módulo en PyPI
Home-page: https://github.com/YoshuDaza
Author: Katto
